MANIFEST.in
README.md
dev_requirements.txt
requirements.txt
setup.py
test_requirements.txt
version.txt
cloudshell/__init__.py
cloudshell/networking/__init__.py
cloudshell/networking/alcatel/__init__.py
cloudshell/networking/alcatel/errors.py
cloudshell/networking/alcatel/autoload/__init__.py
cloudshell/networking/alcatel/autoload/alcatel_generic_snmp_autoload.py
cloudshell/networking/alcatel/cli/__init__.py
cloudshell/networking/alcatel/cli/alcatel_cli_handler.py
cloudshell/networking/alcatel/cli/alcatel_command_modes.py
cloudshell/networking/alcatel/command_actions/__init__.py
cloudshell/networking/alcatel/command_actions/enable_disable_snmp_actions.py
cloudshell/networking/alcatel/command_actions/port_actions.py
cloudshell/networking/alcatel/command_actions/system_actions.py
cloudshell/networking/alcatel/command_actions/vlan_actions.py
cloudshell/networking/alcatel/command_templates/__init__.py
cloudshell/networking/alcatel/command_templates/configuration.py
cloudshell/networking/alcatel/command_templates/enable_disable_snmp.py
cloudshell/networking/alcatel/command_templates/port_template.py
cloudshell/networking/alcatel/command_templates/vlan_template.py
cloudshell/networking/alcatel/flows/__init__.py
cloudshell/networking/alcatel/flows/alcatel_add_vlan_flow.py
cloudshell/networking/alcatel/flows/alcatel_autoload_flow.py
cloudshell/networking/alcatel/flows/alcatel_disable_snmp_flow.py
cloudshell/networking/alcatel/flows/alcatel_enable_snmp_flow.py
cloudshell/networking/alcatel/flows/alcatel_load_firmware_flow.py
cloudshell/networking/alcatel/flows/alcatel_remove_vlan_flow.py
cloudshell/networking/alcatel/flows/alcatel_restore_flow.py
cloudshell/networking/alcatel/flows/alcatel_save_flow.py
cloudshell/networking/alcatel/mibs/ATM-TC-MIB.py
cloudshell/networking/alcatel/mibs/TIMETRA-CHASSIS-MIB.py
cloudshell/networking/alcatel/mibs/TIMETRA-GLOBAL-MIB.py
cloudshell/networking/alcatel/mibs/TIMETRA-PORT-MIB.py
cloudshell/networking/alcatel/mibs/TIMETRA-TC-MIB.py
cloudshell_networking_alcatel.egg-info/PKG-INFO
cloudshell_networking_alcatel.egg-info/SOURCES.txt
cloudshell_networking_alcatel.egg-info/dependency_links.txt
cloudshell_networking_alcatel.egg-info/requires.txt
cloudshell_networking_alcatel.egg-info/top_level.txt
