Metadata-Version: 1.0
Name: cloudshell-networking-alcatel
Version: 1.2.3
Summary: QualiSystems networking Alcatel specific package
Home-page: http://www.qualisystems.com/
Author: QualiSystems
Author-email: info@qualisystems.com
License: UNKNOWN
Platform: UNKNOWN
